availability_checker/__init__.py
availability_checker/checker/__init__.py
availability_checker/checker/config.py
availability_checker/checker/main.py
availability_checker/checker/common/__init__.py
availability_checker/checker/common/common.py
availability_checker/checker/common/utils.py
availability_checker/checker/plugins/__init__.py
availability_checker/checker/plugins/acceleration_vehicle.py
availability_checker/checker/plugins/break_wear.py
availability_checker/checker/plugins/coordinates.py
availability_checker/checker/plugins/engine_oil_pressure.py
availability_checker/checker/plugins/engine_rpm.py
availability_checker/checker/plugins/engine_technology.py
availability_checker/checker/plugins/engine_temperature.py
availability_checker/checker/plugins/fuel_tank_level.py
availability_checker/checker/plugins/global_calculation.py
availability_checker/checker/plugins/id_route.py
availability_checker/checker/plugins/kilometers_vehicle.py
availability_checker/checker/plugins/memory_ram_sts.py
availability_checker/checker/plugins/plugins_config.py
availability_checker/checker/plugins/speed_vehicle.py
availability_checker/checker/plugins/sts_temperature.py
availability_checker/checker/plugins/type_brake.py
availability_checker/checker/plugins/type_bus.py
availability_checker/checker/plugins/vehicle_disconnection.py
availability_checker-0.1.4.dist-info/METADATA
availability_checker-0.1.4.dist-info/WHEEL
availability_checker-0.1.4.dist-info/top_level.txt
availability_checker-0.1.4.dist-info/RECORD
