Metadata-Version: 2.1
Name: availability-checker
Version: 0.1.4
Summary: A package to check the availability of a bunch of variables in P60 trams por ITS
Home-page: https://github.com/melius/availability_data_check.git
Author: Gabriel Gonzalez
Author-email: gabriel.gonzalez@meliusid.com
Classifier: Programming Language :: Python :: 3
Classifier: License :: OSI Approved :: MIT License
Classifier: Operating System :: OS Independent
Requires-Python: >=3.8
Requires-Dist: pandas==2.2.2
